{
    "_id" : "702e92df-206d-4939-8f90-cf5267a2018c",
    "personId" : "a0c60adf-8c95-4369-b267-b72793d13336",
    "firstName" : "Saravanakumar",
    "lastName" : "Vijayakumar",
    "mobileNumber" : "8056657590",
    "totalBalance" : NumberDecimal("300.0"),
    "actualKoolyIncome": NumberDecimal("200.0")
}

{
    "_id" : "bef03b63-b657-48c2-8d4a-2adeb4b07df3",
    "personId" : "b577e802-55db-43af-a837-c7a78bcee4e2",
    "firstName" : "Sakthivel",
    "lastName" : "Vijayakumar",
    "mobileNumber" : "8870121143",
    "totalBalance" : NumberDecimal("500.0"),
    "actualKoolyIncome": NumberDecimal("0.0")
}

{
    "_id" : "2d871ad8-4d1a-442f-ab07-cf60b3fbffbe",
    "personId" : "a4c227bb-bc9f-433c-9d17-5326be44574a",
    "firstName" : "Manikandan",
    "lastName" : "Mohan",
    "mobileNumber" : "8754127814",
    "totalBalance" : NumberDecimal("100.0"),
    "actualKoolyIncome": NumberDecimal("400.0")
}

{
    "_id" : "c5c5ac8d-3802-49f0-a08f-4abc12992e9b",
    "personId" : "e7c96c2f-e225-41a5-83fa-e5392dd2d90d",
    "firstName" : "Godson",
    "lastName" : "Pattudurai",
    "mobileNumber" : "9965858193",
    "totalBalance" : NumberDecimal("0.0"),
    "actualKoolyIncome": NumberDecimal("500.0")
}

{
    "_id" : "7b87bc07-9986-469a-b017-427695b6a843",
    "personId" : "9c56a4d7-2db3-43a4-8a0d-0161140c6a90",
    "firstName" : "Suriyaprabhu",
    "lastName" : "Eswaran",
    "mobileNumber" : "8428942314",
    "totalBalance" : NumberDecimal("0.0"),
    "actualKoolyIncome": NumberDecimal("500.0")
}

{
    "_id" : "1e6911a8-abb3-42ec-bca4-52ce9f659aaf",
    "personId" : "01576540-65c3-407f-9492-84603874692f",
    "firstName" : "Vijayakumar",
    "lastName" : "Subbaiah",
    "mobileNumber" : "9486873503",
    "totalBalance" : NumberDecimal("0.0"),
    "actualKoolyIncome": NumberDecimal("500.0")
}